feeeg/__init__.py
feeeg/test.py
feeeg-0.0.1.dist-info/AUTHORS.rst
feeeg-0.0.1.dist-info/LICENSE
feeeg-0.0.1.dist-info/METADATA
feeeg-0.0.1.dist-info/WHEEL
feeeg-0.0.1.dist-info/top_level.txt
feeeg-0.0.1.dist-info/RECORD
